[{"model": "device.communicationdevice", "pk": 1, "fields": {"name": "RFAN"}}, {"model": "device.communicationdevice", "pk": 2, "fields": {"name": "RFDI"}}, {"model": "device.communicationdevice", "pk": 3, "fields": {"name": "GPRS"}}, {"model": "device.communicationdevice", "pk": 4, "fields": {"name": "GSM"}}, {"model": "device.communicationdevice", "pk": 5, "fields": {"name": "SMS"}}, {"model": "device.typedevice", "pk": 1, "fields": {"name": "Datalogger"}}, {"model": "device.typedevice", "pk": 2, "fields": {"name": "M\u00f3dem anal\u00f3gico"}}, {"model": "device.typedevice", "pk": 3, "fields": {"name": "M\u00f3dem digital"}}, {"model": "device.typedevice", "pk": 4, "fields": {"name": "Radar"}}, {"model": "device.typedevice", "pk": 5, "fields": {"name": "Antena"}}, {"model": "device.typedevice", "pk": 6, "fields": {"name": "PLC"}}, {"model": "device.typedevice", "pk": 7, "fields": {"name": "SAI"}}, {"model": "device.typedevice", "pk": 8, "fields": {"name": "Magnetot\u00e9rmico"}}, {"model": "device.typedevice", "pk": 9, "fields": {"name": "Diferencial"}}, {"model": "device.typedevice", "pk": 10, "fields": {"name": "Rel\u00e9"}}, {"model": "device.typedevice", "pk": 11, "fields": {"name": "Cargador bater\u00eda"}}, {"model": "device.typedevice", "pk": 12, "fields": {"name": "Arrancador"}}, {"model": "device.typedevice", "pk": 13, "fields": {"name": "Variador frecuencia"}}, {"model": "device.typedevice", "pk": 14, "fields": {"name": "Bomba"}}, {"model": "device.typedevice", "pk": 15, "fields": {"name": "Boya"}}, {"model": "device.typedevice", "pk": 16, "fields": {"name": "Sonda presi\u00f3n"}}, {"model": "device.typedevice", "pk": 17, "fields": {"name": "Fuente alimentaci\u00f3n"}}, {"model": "device.typedevice", "pk": 18, "fields": {"name": "Switch"}}, {"model": "device.typedevice", "pk": 19, "fields": {"name": "HMI"}}, {"model": "device.typedevice", "pk": 20, "fields": {"name": "Visor Caudal\u00edmetro"}}, {"model": "device.branddevice", "pk": 1, "fields": {"name": "Siemens"}}, {"model": "device.branddevice", "pk": 2, "fields": {"name": "Cargatronic"}}, {"model": "device.branddevice", "pk": 3, "fields": {"name": "Sofrel"}}, {"model": "device.branddevice", "pk": 4, "fields": {"name": "Motorola"}}, {"model": "device.branddevice", "pk": 5, "fields": {"name": "Omron"}}, {"model": "device.branddevice", "pk": 6, "fields": {"name": "Allen-bradley"}}, {"model": "device.branddevice", "pk": 7, "fields": {"name": "Mejoras"}}]